admin_log/__init__.py
admin_log/admin.py
admin_log/fields.py
admin_log/middleware.py
admin_log/models.py
admin_log/locale/ru/LC_MESSAGES/django.po
django_admin_blame-1.1.1.dist-info/LICENSE
django_admin_blame-1.1.1.dist-info/METADATA
django_admin_blame-1.1.1.dist-info/WHEEL
django_admin_blame-1.1.1.dist-info/top_level.txt
django_admin_blame-1.1.1.dist-info/RECORD
