Metadata-Version: 2.1
Name: django-admin-blame
Version: 1.1.1
Summary: Tools for logging changes made from Django admin
Home-page: https://github.com/just-work/django-admin-blame
Author: Sergey Tikhonov
Author-email: zimbler@gmail.com
License: MIT
Classifier: Development Status :: 5 - Production/Stable
Classifier: Environment :: Console
Classifier: Framework :: Django :: 2.2
Classifier: Framework :: Django :: 3.0
Classifier: Framework :: Django :: 3.1
Classifier: Framework :: Django :: 3.2
Classifier: Framework :: Django :: 4.0
Classifier: Framework :: Django :: 4.1
Classifier: Operating System :: POSIX
Classifier: Programming Language :: Python :: 3.6
Classifier: Programming Language :: Python :: 3.7
Classifier: Programming Language :: Python :: 3.8
Classifier: Programming Language :: Python :: 3.9
Classifier: Programming Language :: Python :: 3.10
Classifier: Topic :: Internet :: WWW/HTTP :: Dynamic Content :: Content Management System
License-File: LICENSE
Requires-Dist: Django (<4.2,>=2.2)
Requires-Dist: django-model-utils (<4.3.0,>=4.2.0)
